imm/_path.py
imm/_output.py
imm/_interval.py
imm/build_ext.py
imm/_results.py
imm/_lprob.py
imm/_hmm.py
imm/_dp.py
imm/_cdata.py
imm/_sequence_table.py
imm/__init__.py
imm/_step.py
imm/_result.py
imm/_sequence.py
imm/imm.h
imm/_alphabet_table.py
imm/_state.py
imm/_fragment.py
imm/_ffi.abi3.so
imm/_input.py
imm/_testit.py
imm/testing.py
imm/_alphabet.py
imm/wrap.py
imm/_model.py
imm/test/test_sequence.py
imm/test/__init__.py
imm/test/test_io.py
imm/test/test_state.py
imm/test/test_sequence_table.py
imm/test/test_alphabet.py
imm/test/test_hmm.py
imm/test/test_lprob.py
imm/test/test_fragment.py
imm/.dylibs/libimm.0.0.9.dylib
imm-0.0.2.dist-info/LICENSE.md
imm-0.0.2.dist-info/RECORD
imm-0.0.2.dist-info/WHEEL
imm-0.0.2.dist-info/top_level.txt
imm-0.0.2.dist-info/METADATA
